convertbonds/BS.py
convertbonds/Monte_Carlo.py
convertbonds/__init__.py
convertbonds-0.0.1.dist-info/licenses/LICENSE
convertbonds-0.0.1.dist-info/METADATA
convertbonds-0.0.1.dist-info/WHEEL
convertbonds-0.0.1.dist-info/entry_points.txt
convertbonds-0.0.1.dist-info/top_level.txt
convertbonds-0.0.1.dist-info/RECORD
